fluxflow_training/__init__.py
fluxflow_training/py.typed
fluxflow_training/data/__init__.py
fluxflow_training/data/datasets.py
fluxflow_training/data/transforms.py
fluxflow_training/scripts/__init__.py
fluxflow_training/scripts/generate.py
fluxflow_training/scripts/generate_training_graphs.py
fluxflow_training/scripts/train.py
fluxflow_training/training/__init__.py
fluxflow_training/training/cfg_inference.py
fluxflow_training/training/cfg_utils.py
fluxflow_training/training/checkpoint_manager.py
fluxflow_training/training/flow_trainer.py
fluxflow_training/training/losses.py
fluxflow_training/training/optimizer_factory.py
fluxflow_training/training/pipeline_config.py
fluxflow_training/training/pipeline_orchestrator.py
fluxflow_training/training/progress_logger.py
fluxflow_training/training/scheduler_factory.py
fluxflow_training/training/schedulers.py
fluxflow_training/training/training_mode.py
fluxflow_training/training/utils.py
fluxflow_training/training/vae_trainer.py
fluxflow_training-0.5.1.dist-info/licenses/LICENSE
fluxflow_training-0.5.1.dist-info/METADATA
fluxflow_training-0.5.1.dist-info/WHEEL
fluxflow_training-0.5.1.dist-info/entry_points.txt
fluxflow_training-0.5.1.dist-info/top_level.txt
fluxflow_training-0.5.1.dist-info/RECORD
